Metadata-Version: 2.4
Name: pluto-ai
Version: 1.0.0
Summary: AI-powered code security vulnerability scanner
Home-page: https://github.com/0xsaikat/pluto
Author: 0xSaikat
Author-email: 0xSaikat <contact@hackbit.org>
License: MIT
Project-URL: Homepage, https://hackbit.org
Project-URL: Repository, https://github.com/0xsaikat/pluto
Project-URL: Issues, https://github.com/0xsaikat/pluto/issues
Keywords: security,vulnerability,scanner,code-analysis,ai,static-analysis
Classifier: Development Status :: 4 - Beta
Classifier: Intended Audience :: Developers
Classifier: Topic :: Security
Classifier: License :: OSI Approved :: MIT License
Classifier: Programming Language :: Python :: 3
Classifier: Programming Language :: Python :: 3.7
Classifier: Programming Language :: Python :: 3.8
Classifier: Programming Language :: Python :: 3.9
Classifier: Programming Language :: Python :: 3.10
Classifier: Programming Language :: Python :: 3.11
Requires-Python: >=3.7
Requires-Dist: click>=8.0.0
Requires-Dist: anthropic>=0.18.0
Requires-Dist: openai>=1.0.0
Requires-Dist: requests>=2.28.0
Requires-Dist: GitPython>=3.1.0
Requires-Dist: reportlab>=4.0.0
Dynamic: author
Dynamic: home-page
Dynamic: requires-python
